setup.cfg
setup.py
stuffed/__init__.py
stuffed/address.py
stuffed/creditcard.py
stuffed/email.py
stuffed/tests.py
stuffed.egg-info/PKG-INFO
stuffed.egg-info/SOURCES.txt
stuffed.egg-info/dependency_links.txt
stuffed.egg-info/requires.txt
stuffed.egg-info/top_level.txt
stuffed.egg-info/zip-safe