Metadata-Version: 1.0
Name: stuffed
Version: 0.0.3
Summary: All your belongings
Home-page: https://github.com/stevepeak/stuffed
Author: @iopeak
Author-email: steve@stevepeak.net
License: Apache v2
Keywords: credit card address phone
Platform: UNKNOWN
Classifier: Development Status :: 1 - Planning
Classifier: Environment :: Plugins
Classifier: License :: OSI Approved :: Apache Software License
Classifier: Programming Language :: Python
Classifier: Programming Language :: Python :: 2.7
Classifier: Topic :: Utilities
